matrice_common/__init__.py
matrice_common/__init__.pyi
matrice_common/compute.py
matrice_common/compute.pyi
matrice_common/py.typed
matrice_common/rpc.py
matrice_common/rpc.pyi
matrice_common/session.py
matrice_common/session.pyi
matrice_common/token_auth.py
matrice_common/token_auth.pyi
matrice_common/utils.py
matrice_common/utils.pyi
matrice_common/optimize/__init__.py
matrice_common/optimize/__init__.pyi
matrice_common/optimize/frame_optimizer.py
matrice_common/optimize/frame_optimizer.pyi
matrice_common/optimize/result_cache.py
matrice_common/optimize/result_cache.pyi
matrice_common/optimize/roi_processor.py
matrice_common/optimize/roi_processor.pyi
matrice_common/stream/__init__.py
matrice_common/stream/__init__.pyi
matrice_common/stream/cuda_shm_ring_buffer.py
matrice_common/stream/cuda_shm_ring_buffer.pyi
matrice_common/stream/event_listener.py
matrice_common/stream/event_listener.pyi
matrice_common/stream/gpu_camera_map.py
matrice_common/stream/gpu_camera_map.pyi
matrice_common/stream/kafka_stream.py
matrice_common/stream/kafka_stream.pyi
matrice_common/stream/matrice_stream.py
matrice_common/stream/matrice_stream.pyi
matrice_common/stream/matrice_stream_usage_example.py
matrice_common/stream/matrice_stream_usage_example.pyi
matrice_common/stream/redis_stream.py
matrice_common/stream/redis_stream.pyi
matrice_common/stream/shm_ring_buffer.py
matrice_common/stream/shm_ring_buffer.pyi
matrice_common/video/__init__.py
matrice_common/video/__init__.pyi
matrice_common/video/h265_auto.py
matrice_common/video/h265_auto.pyi
matrice_common/video/h265_consumer_examples.py
matrice_common/video/h265_consumer_examples.pyi
matrice_common/video/h265_processor.py
matrice_common/video/h265_processor.pyi
matrice_common/video/h265_processor_linux.py
matrice_common/video/h265_processor_linux.pyi
matrice_common/video/h265_video_processor.py
matrice_common/video/h265_video_processor.pyi
matrice_common-0.1.75.dist-info/licenses/LICENSE.txt
matrice_common-0.1.75.dist-info/METADATA
matrice_common-0.1.75.dist-info/WHEEL
matrice_common-0.1.75.dist-info/top_level.txt
matrice_common-0.1.75.dist-info/RECORD
